{
  "_class": "shapeGroup",
  "clippingMaskMode": 0,
  "do_objectID": "607F7876-A3F1-4A35-BA6A-9C18F7AE2208",
  "exportOptions": {
    "_class": "exportOptions",
    "exportFormats": [
    ],
    "includedLayerIds": [
    ],
    "layerOptions": 0,
    "shouldTrim": false
  },
  "frame": {
    "_class": "rect",
    "constrainProportions": true,
    "height": 40,
    "width": 40,
    "x": -959,
    "y": -383
  },
  "hasClickThrough": false,
  "hasClippingMask": false,
  "isFlippedHorizontal": false,
  "isFlippedVertical": false,
  "isLocked": false,
  "isVisible": true,
  "layerListExpandedType": 1,
  "layers": [
    {
      "class": "rectangle",
      "id": "BA8F0ED9-F61C-4492-B6A9-47D3030FE398"
    }
  ],
  "name": "Rectangle Copy 5",
  "nameIsFixed": false,
  "resizingConstraint": 63,
  "resizingType": 0,
  "rotation": 0,
  "shouldBreakMaskChain": false,
  "style": {
    "sharedObjectID": "12FAFDDB-3C90-438F-A30F-19C698FFA0F5"
  },
  "userInfo": {
    "com.animaapp.stc-sketch-plugin": {
      "kModelPropertiesKey": {
        "constraints": {
          "aspectRatio": {
            "constant": 40,
            "enabled": 1,
            "modelID": "constraint_7d9d52ef-f14b-42c3-8348-9238659cd27d",
            "model_class": "ADModelConstraint",
            "model_version": 0.1,
            "multiplier": 40
          },
          "automatic": 1,
          "modelID": "viewConstraints_5308a938-258c-4717-829d-82d965a75dc1",
          "model_class": "ADModelViewConstraints",
          "model_version": 0.1,
          "scaleFactor": 1
        }
      }
    }
  },
  "windingRule": 1
}